dividend/__init__.py
dividend/async_requests.py
dividend/errors.py
dividend/screener.py
dividend/parsers/__init__.py
dividend/parsers/attributes.py
dividend/parsers/dividend_growth.py
dividend/parsers/overview.py
dividend/parsers/parse_table.py
dividend-1.0.3.dist-info/METADATA
dividend-1.0.3.dist-info/WHEEL
dividend-1.0.3.dist-info/top_level.txt
dividend-1.0.3.dist-info/RECORD
