Metadata-Version: 2.1
Name: dividend
Version: 1.0.3
Summary: The Unofficial API for Dividend.com
Home-page: http://github.com/tke578/dividend
Author: Andrew Garcia
Author-email: tke578@gmail.com
License: MIT
Keywords: dividend,api,screener,dividend api
Platform: UNKNOWN
Requires-Dist: requests
Requires-Dist: aiohttp
